entryutils/__init__.py
entryutils/lib2.py
entryutils/main.py
entryutils/queries/createaccount.txt
entryutils/queries/login.txt
entryutils-0.0.6.dist-info/LICENSE
entryutils-0.0.6.dist-info/METADATA
entryutils-0.0.6.dist-info/WHEEL
entryutils-0.0.6.dist-info/top_level.txt
entryutils-0.0.6.dist-info/RECORD
