Metadata-Version: 2.1
Name: entryutils
Version: 0.0.6
Summary: Package for AJAX in Entry (Programming Site).
Author: lemonbbt
License: Permission is hereby granted, free of charge, to any person obtaining a copy
Classifier: Programming Language :: Python :: 3
Classifier: License :: OSI Approved :: MIT License
Classifier: Operating System :: OS Independent
Requires-Python: >=3.7
License-File: LICENSE
Requires-Dist: requests
